[
  {
    "id": 1,
    "city": "mumbai",
    "service": [
      "mumbai to delhi cab",
      "taxi from mumbai to delhi",
      "mumbai to delhi car rental",
      "car from mumbai to delhi",
      "mumbai to delhi cab fare",
      "cab from mumbai to delhi"
    ]
  },
  {
    "id": 2,
    "city": "delhi",
    "service": [
      "delhi to chandigarh cab",
      "delhi to agra cab",
      "delhi to jaipur cab",
      "taxi from delhi to chandigarh",
      "delhi to agra taxi",
      "taxi from delhi to jaipur",
      "delhi to chandigarh taxi fare",
      "delhi to agra cab booking",
      "delhi to chandigarh cab farev",
      "delhi to jaipur cab booking",
      "delhi to agra cab fare",
      "delhi to chd taxi",
      "delhi to chandigarh cab booking",
      "delhi to agra taxi booking",
      "cab from delhi to chandigarh",
      "delhi to jaipur taxi bookingv",
      "book taxi delhi to agra",
      "delhi to haridwar taxi",
      "delhi to haridwar cab",
      "delhi to manali cab",
      "delhi to dehradun cab",
      "delhi to dehradun taxi",
      "delhi to manali taxiv",
      "delhi to haridwar cab booking",
      "cab booking delhi to dehradun",
      "delhi to rishikesh cab",
      "delhi to rishikesh taxi",
      "delhi to rishikesh cab booking",
      "delhi to vrindavan cab",
      "delhi to nainital cab",
      "delhi to nainital taxi",
      "delhi to vrindavan taxi",
      "delhi to nainital cab booking",
      "delhi to nainital cab fare",
      "delhi to outstation taxi",
      "delhi to shimla cab",
      "delhi to mussoorie cab",
      "delhi to mathura cab",
      "delhi to shimla taxi",
      "delhi to agra cab service",
      "delhi to agra taxi service",
      "delhi to mussoorie taxi",
      "taxi from delhi to mathura",
      "delhi to shimla cab booking",
      "taxi service delhi to agra",
      "delhi to ludhiana taxi",
      "delhi to ludhiana cab",
      "cab booking for delhi to agra",
      "taxi for delhi to agra",
      "delhi to manali cab fare",
      "delhi to manali taxi fare",
      "taxi service delhi to dehradun",
      "delhi to jalandhar taxi",
      "delhi to jalandhar cab",
      "delhi to agra taxi fare",
      "delhi to dehradun taxi service",
      "delhi to amritsar taxi",
      "delhi to amritsar cab",
      "delhi to jaipur taxi fare",
      "delhi to agra taxi price",
      "delhi to agra cab price",
      "delhi to agra cab cost",
      "delhi to jaipur cab service",
      "delhi to dehradun cab service",
      "delhi to jaipur taxi service",
      "taxi service delhi to jaipur",
      "delhi to agra taxi charges",
      "delhi to jaipur taxi price",
      "cab service delhi to dehradun",
      "delhi to agra taxi cost",
      "delhi to amritsar cab fare",
      "delhi to haldwani cab",
      "delhi to haldwani taxi",
      "delhi to jaipur cab price",
      "delhi to jaipur cab cost",
      "fare from delhi to agra by cab",
      "delhi to chandigarh taxi service",
      "delhi to shimla taxi fare",
      "delhi to dehradun taxi fare",
      "delhi to dehradun taxi price",
      "delhi to shimla taxi price",
      "delhi to dehradun cab fare",
      "delhi to shimla cab price",
      "cab from delhi to lucknow",
      "taxi from delhi to lucknow",
      "delhi to dehradun cab charges",
      "one way cab from delhi to jaipur",
      "delhi to jaipur one way taxi",
      "delhi to lucknow taxi",
      "delhi to jaipur cab one way",
      "delhi to lucknow cab",
      "delhi to shimla cab charges",
      "delhi to dehradun taxi charges",
      "delhi to shimla taxi cost",
      "cabs from delhi to lucknow"
    ]
  },
  {
    "id": 3,
    "city": "agra",
    "service": [
      "agra to delhi cab",
      "agra to delhi taxi",
      "agra to delhi cab booking",
      "cab from agra to delhi",
      "agra delhi taxi",
      "agra to delhi taxi service",
      "cab for agra from delhi",
      "taxi for agra from delhi",
      "delhi agra taxi price",
      "delhi agra car",
      "agra to delhi taxi fare",
      "agra to delhi cab fare",
      "agra to delhi taxi price",
      "agra to delhi cab price",
      "agra to delhi taxi cost",
      "delhi airport to agra cab",
      "taxi from delhi airport to agra",
      "new delhi airport to agra taxi",
      "cab from delhi airport to agra",
      "one way taxi from agra to delhi",
      "agra to delhi cab one way",
      "one way cab agra to delhi",
      "agra to delhi taxi one way",
      "agra to delhi airport cab",
      "agra to delhi car",
      "taxi from agra to delhi airport",
      "agra to delhi car booking",
      "agra to delhi airport taxi",
      "agra to delhi cab service",
      "agra to delhi airport taxi fare",
      "delhi airport to agra taxi price",
      "delhi airport to agra taxi fare",
      "agra to delhi car rental",
      "agra to delhi car fare",
      "delhi agra taxi fare",
      "agra to new delhi cab",
      "agra to delhi airport taxi one way",
      "agra to delhi cab charges",
      "taxi service from agra to delhi",
      "agra to new delhi taxi fare",
      "car rental delhi agra tour",
      "delhi agra taxi tourv",
      "delhi airport to agra taxi one way fare",
      "agra to delhi car service",
      "agra to delhi uber",
      "book cab from agra to delhi",
      "cab service from agra to delhiv",
      "delhi agra delhi cab",
      "one side taxi from agra to delhi",
      "private taxi from agra to delhi",
      "uber agra to delhi"
    ]
  },
  {
    "id": 4,
    "city": "ambala",
    "service": [
      "ambala to delhi cab",
      "ambala to delhi taxi",
      "ambala to delhi taxi service",
      "ambala to delhi taxi fare",
      "ambala to delhi airport taxi",
      "ambala to delhi taxi price",
      "delhi airport to ambala taxi"
    ]
  },
  {
    "id": 5,
    "city": "amritsar",
    "service": [
      "amritsar to delhi taxi",
      "amritsar to delhi cab",
      "amritsar to delhi cab fare",
      "taxi fare from amritsar to delhi",
      "taxi amritsar to delhi",
      "amritsar to delhi taxi service",
      "taxi from delhi airport to amritsar",
      "one way taxi amritsar to delhi",
      "amritsar to delhi one way taxi",
      "delhi airport to amritsar taxi",
      "amritsar to delhi taxi fare",
      "amritsar to delhi airport taxi",
      "taxi from amritsar to delhi airport",
      "amritsar to delhi car",
      "amritsar to delhi car fare",
      "amritsar to new delhi taxi service",
      "delhi airport to amritsar taxi fare"
    ]
  },
  {
    "id": 6,
    "city": "chandigarh",
    "service": [
      "chd to delhi taxi",
      "taxi from chandigarh to delhi",
      "cab from chandigarh to delhi",
      "taxi for chandigarh from delhi",
      "chandigarh to delhi taxi service",
      "chd to delhi taxi service",
      "chandigarh to delhi one way taxi",
      "one way taxi chandigarh to delhi",
      "one way cab chandigarh to delhi",
      "chandigarh delhi one way taxi",
      "chd to delhi one way taxi",
      "chd to delhi cab",
      "delhi airport to chandigarh taxi",
      "delhi airport to chandigarh cab",
      "chandigarh to delhi drop taxichandigarh to delhi drop taxi",
      "new delhi airport to chandigarh taxi",
      "taxi from delhi airport to chandigarhv",
      "chandigarh to delhi airport taxi",
      "chandigarh to delhi airport cab",
      "cab chandigarh to delhi airport",
      "chd to delhi airport taxi",
      "chandigarh to delhi airport drop taxi",
      "chandigarh to delhi airport one way taxi",
      "chandigarh to delhi taxi drop",
      "one way taxi chandigarh to delhi airport",
      "one way taxi from chandigarh to delhi airport",
      "taxi service chandigarh to delhi",
      "chandigarh to delhi one way taxi service",
      "cab service chandigarh to delhi",
      "chandigarh to delhi cab service",
      "chandigarh to delhi taxi chandigarh",
      "chandigarh to delhi taxi fare",
      "chandigarh to delhi taxi one way",
      "one way taxi from chandigarh to delhi",
      "cheapest taxi from chandigarh to delhi",
      "chandigarh to delhi airport taxi price",
      "delhi airport to chandigarh taxi service",
      "chandigarh to delhi cab price",
      "chandigarh to delhi one way taxi chandigarh",
      "chandigarh to delhi taxi service one way",
      "chandigarh to delhi taxi price",
      "taxi fare from chandigarh to delhi",
      "chandigarh to delhi cab fare",
      "chandigarh to delhi airport one way taxi service",
      "taxi fare chandigarh to delhi",
      "one way taxi service chandigarh to delhi",
      "chandigarh to delhi airport taxi fare",
      "chandigarh to delhi airport taxi service",
      "chandigarh to delhi by car",
      "taxi fare from chandigarh to delhi airport",
      "one way taxi from delhi airport to chandigarh",
      "chandigarh to delhi one way taxi fare",
      "chandigarh to delhi cab booking",
      "chandigarh to delhi car fare",
      "one way taxi service from chandigarh to delhi airport",
      "delhi airport to chandigarh taxi fare",
      "chandigarh to delhi car",
      "taxi from chandigarh to delhi airport",
      "taxi service chandigarh to delhi airport",
      "taxi service from chandigarh to delhi airport",
      "delhi chandigarh taxi one way",
      "taxi service from delhi airport to chandigarh",
      "chandigarh to delhi one side taxi",
      "chandigarh to delhi taxi distancev",
      "chandigarh to new delhi taxi fare",
      "delhi airport to chandigarh cab fare",
      "delhi airport to chandigarh drop taxi",
      "one way taxi delhi airport to chandigarh",
      "chandigarh to new delhi cab",
      "chandigarh to new delhi taxi",
      "chandigarh to delhi airport taxi charges",
      "chandigarh to delhi cab rates",
      "chandigarh to delhi car rental",
      "taxi delhi chandigarh",
      "one way cab from delhi airport to chandigarh",
      "cab for chandigarh to delhi",
      "book cab from chandigarh to delhi",
      "chandigarh to delhi cab charges",
      "car rental chandigarh to delhi",
      "chandigarh to delhi airport one side taxi"
    ]
  },
  {
    "id": 7,
    "city": "dehradun",
    "service": [
      "dehradun to delhi cab",
      "taxi from dehradun to delhi",
      "dehradun to delhi cab booking",
      "dehradun to delhi taxi service",
      "taxi service dehradun to delhi",
      "dehradun to delhi cab service",
      "dehradun to delhi taxi price",
      "delhi airport to dehradun taxi",
      "cab from delhi airport to dehradun",
      "delhi airport to dehradun cab",
      "taxi fare from dehradun to delhi",
      "dehradun to delhi cab fare",
      "dehradun to delhi cab price",
      "dehradun to delhi taxi charges",
      "dehradun to delhi airport cab",
      "taxi from dehradun to delhi airport",
      "dehradun to delhi by car",
      "delhi airport to dehradun taxi fare",
      "dehradun to delhi car",
      "dehradun to delhi taxi time",
      "taxi service in dehradun to delhi",
      "taxi for dehradun from delhi",
      "dehradun to delhi car booking",
      "one way taxi from dehradun to delhi",
      "dehradun to delhi taxi booking",
      "one way taxi dehradun to delhi",
      "cheapest cab from dehradun to delhi",
      "dehradun to delhi taxi cost",
      "book cab from dehradun to delhi",
      "dehradun to delhi car fare"
    ]
  },
  {
    "id": 8,
    "city": "haridwar",
    "service": [
      "taxi from haridwar to delhi",
      "cab from haridwar to delhi",
      "taxi for haridwar from delhi",
      "haridwar to delhi cab booking",
      "delhi airport to haridwar taxi",
      "delhi airport to haridwar cab",
      "new delhi airport to haridwar taxi",
      "haridwar to delhi by car",
      "haridwar to delhi car",
      "haridwar to delhi cab fare",
      "haridwar to delhi cab price",
      "delhi airport to haridwar taxi fare",
      "haridwar to delhi car fare",
      "haridwar to delhi one way taxi",
      "cab for haridwar from delhi",
      "cab haridwar to delhi",
      "delhi haridwar cab service",
      "delhi airport to haridwar car fare",
      "delhi haridwar taxi service",
      "haridwar to new delhi car fare",
      "taxi fare from delhi airport to haridwar",
      "taxi service from haridwar to delhi",
      "one way taxi from haridwar to delhi",
      "haridwar to new delhi taxi fare",
      "taxi fare from haridwar to delhi",
      "delhi haridwar rishikesh taxi service",
      "book cab from haridwar to delhi",
      "haridwar to delhi car booking"
    ]
  },
  {
    "id": 9,
    "city": "jaipur",
    "service": [
      "jaipur to delhi cab",
      "taxi from jaipur to delhi",
      "jaipur to delhi cab booking",
      "one way taxi jaipur to delhi",
      "one way cab jaipur to delhi",
      "jaipur to delhi taxi service",
      "jaipur to delhi car",
      "jaipur to delhi cab fare",
      "jaipur to delhi taxi price",
      "jaipur to delhi cab price",
      "jaipur to delhi airport cab",
      "jaipur to delhi cab service",
      "jaipur to delhi airport taxi",
      "taxi service from jaipur to delhi",
      "jaipur to delhi taxi fare",
      "taxi from delhi airport to jaipur",
      "cab from delhi airport to jaipur",
      "delhi airport to jaipur taxi",
      "jaipur to delhi taxi charges",
      "one way taxi jaipur to delhi airport",
      "jaipur to delhi one way taxi fare",
      "jaipur delhi taxi service jaipur rajasthan",
      "jaipur to delhi one way taxi service",
      "jaipur to delhi taxi one way",
      "jaipur to delhi car rental",
      "delhi airport to jaipur taxi fare",
      "taxi fare from delhi airport to jaipur",
      "jaipur to delhi airport drop taxi",
      "one side taxi jaipur to delhi",
      "jaipur to delhi distance by taxi",
      "jaipur to delhi airport one way taxi",
      "jaipur to delhi car service",
      "jaipur to delhi cab service price",
      "delhi airport to jaipur one way taxi",
      "jaipur to delhi taxi service fare",
      "taxi for jaipur to delhi",
      "jaipur to delhi car rental price",
      "jaipur to delhi car fare",
      "cab for jaipur to delhi",
      "jaipur to delhi taxi car",
      "cab from jaipur to delhi one way",
      "cab service from jaipur to delhi",
      "delhi airport drop from jaipur",
      "cab booking jaipur to delhi",
      "book cab from jaipur to delhi",
      "jaipur to delhi cab service fare",
      "taxi service from delhi airport to jaipur",
      "jaipur to delhi drop",
      "one way taxi from delhi airport to jaipur",
      "car rental from jaipur to delhi"
    ]
  },
  {
    "id": 10,
    "city": "jalandhar",
    "service": [
      "jalandhar to delhi taxi",
      "jalandhar to delhi cab",
      "jalandhar to delhi taxi service",
      "jalandhar to delhi one way taxi",
      "one way taxi jalandhar to delhi",
      "jalandhar to delhi airport taxi",
      "one way taxi from jalandhar to delhi airport",
      "taxi service jalandhar to delhi airport",
      "jalandhar to delhi taxi price",
      "taxi jalandhar to delhi airport",
      "jalandhar to delhi taxi fare",
      "jalandhar to delhi airport taxi fare",
      "jalandhar to delhi by car",
      "jalandhar to delhi airport taxi service",
      "taxi service jalandhar to delhi"
    ]
  },
  {
    "id": 11,
    "city": "lucknow",
    "service": [
      "lucknow to delhi taxi",
      "lucknow to delhi cab",
      "lucknow to delhi car",
      "lucknow to delhi taxi fare",
      "lucknow to delhi cab price",
      "lucknow to delhi taxi service",
      "lucknow to delhi cab fare",
      "lucknow to delhi car rental price",
      "lucknow to delhi taxi price",
      "one way cab from lucknow to delhi"
    ]
  },
  {
    "id": 12,
    "city": "ludhiana",
    "service": [
      "ludhiana to delhi taxi",
      "ludhiana to delhi cab",
      "ludhiana to delhi taxi service",
      "one way taxi ludhiana to delhi",
      "ludhiana to delhi airport taxi",
      "taxi ludhiana to delhi airport",
      "ludhiana to delhi cab service",
      "taxi service ludhiana to delhi",
      "ludhiana to delhi taxi price",
      "ludhiana to delhi taxi one way",
      "ludhiana to delhi airport taxi fare",
      "one way taxi ludhiana to delhi airport",
      "ludhiana to delhi airport taxi service",
      "ludhiana to delhi taxi fare",
      "ludhiana to delhi by car",
      "ludhiana to delhi airport cab",
      "one way taxi service ludhiana to delhi",
      "ludhiana to delhi car",
      "ludhiana to delhi one way taxi service",
      "ludhiana to delhi innova taxi",
      "taxi fare from ludhiana to delhi airport",
      "taxi service in ludhiana to delhi",
      "ludhiana to delhi taxi service price"
    ]
  },
  {
    "id": 14,
    "city": "manali",
    "service": [
      "manali to delhi cab",
      "manali to delhi taxi",
      "cab manali to delhi",
      "manali to delhi cab booking",
      "manali to delhi taxi fare",
      "manali to delhi cab fare",
      "manali to delhi car rental",
      "cab for manali from delhi",
      "taxi for manali from delhi",
      "manali to delhi distance by cab",
      "manali to delhi cab price",
      "manali to delhi car fare",
      "manali to delhi taxi service",
      "taxi from manali to delhi",
      "manali to delhi car",
      "manali to delhi cab service",
      "manali to delhi airport taxi service",
      "manali to delhi by car cost",
      "manali to delhi distance taxi fare",
      "manali to delhi innova fare",
      "manali to delhi one way taxi"
    ]
  },
  {
    "id": 15,
    "city": "mathura",
    "service": [
      "cab from mathura to delhi",
      "mathura to delhi taxi",
      "mathura to delhi cab",
      "mathura to delhi taxi fare",
      "mathura to delhi cab fare",
      "mathura to delhi cab service",
      "mathura to delhi by car",
      "mathura to delhi car rental"
    ]
  },
  {
    "id": 16,
    "city": "patiala",
    "service": [
      "patiala to delhi taxi",
      "patiala to delhi cab",
      "patiala to delhi taxi service",
      "patiala to delhi taxi price",
      "one way taxi patiala to delhi",
      "taxi service patiala to delhi",
      "one way taxi service patiala to delhi",
      "patiala to delhi airport taxi service",
      "patiala to delhi by car",
      "patiala to delhi one way taxi",
      "patiala to delhi taxi fare"
    ]
  },
  {
    "id": 17,
    "city": "shimla",
    "service": [
      "shimla to delhi cab",
      "shimla to delhi taxi",
      "shimla to delhi taxi fare",
      "shimla to delhi cab fare",
      "shimla to delhi cab price",
      "shimla to new delhi taxi service",
      "shimla to delhi car fare"
    ]
  },
  {
    "id": 18,
    "city": "vrindavan",
    "service": [
      "delhi vrindavan cab",
      "vrindavan to delhi cab",
      "taxi from vrindavan to delhi",
      "vrindavan to delhi airport taxi",
      "taxi fare from vrindavan to delhi",
      "vrindavan to delhi by car",
      "taxi for vrindavan from delhi",
      "vrindavan to new delhi taxi service"
    ]
  }
]
